{"cameraMode":{"drawMode":0,"name":"Shaded","section":"Shading Mode"},"sceneLighting":true,"audioPlay":false,"sceneViewState":{"m_AlwaysRefresh":false,"showFog":true,"showSkybox":false,"showFlares":true,"showImageEffects":true,"showParticleSystems":true,"showVisualEffectGraphs":true,"m_FxEnabled":true},"in2DMode":false,"pivot":{"x":5.3418378829956059,"y":80.5029525756836,"z":98.04754638671875},"rotation":{"x":-0.3013535141944885,"y":-0.038994524627923968,"z":0.012222259305417538,"w":-0.952659547328949},"size":6.662633419036865,"orthographic":false}