{"cameraMode":{"drawMode":0,"name":"Shaded","section":"Shading Mode"},"sceneLighting":true,"audioPlay":false,"sceneViewState":{"m_AlwaysRefresh":false,"showFog":true,"showSkybox":true,"showFlares":true,"showImageEffects":true,"showParticleSystems":true,"showVisualEffectGraphs":true,"m_FxEnabled":true},"in2DMode":false,"pivot":{"x":0.0,"y":5.0,"z":97.14826965332031},"rotation":{"x":-0.08749224245548248,"y":0.906858503818512,"z":-0.23349109292030335,"w":-0.33979177474975588},"size":15.529693603515625,"orthographic":false}