{"cameraMode":{"drawMode":0,"name":"Shaded","section":"Shading Mode"},"sceneLighting":true,"audioPlay":false,"sceneViewState":{"m_AlwaysRefresh":false,"showFog":true,"showSkybox":false,"showFlares":true,"showImageEffects":true,"showParticleSystems":true,"showVisualEffectGraphs":true,"m_FxEnabled":true},"in2DMode":false,"pivot":{"x":-61.739906311035159,"y":44.20334243774414,"z":58.86597442626953},"rotation":{"x":-0.20504476130008698,"y":0.7753156423568726,"z":-0.312293142080307,"w":-0.509295642375946},"size":40.19976806640625,"orthographic":false}