{"cameraMode":{"drawMode":0,"name":"Shaded","section":"Shading Mode"},"sceneLighting":false,"audioPlay":false,"sceneViewState":{"m_AlwaysRefresh":false,"showFog":true,"showSkybox":false,"showFlares":true,"showImageEffects":true,"showParticleSystems":true,"showVisualEffectGraphs":true,"m_FxEnabled":true},"in2DMode":false,"pivot":{"x":-2.0444326400756838,"y":2.8679990768432619,"z":0.012516498565673828},"rotation":{"x":0.2136574238538742,"y":0.44903454184532168,"z":-0.11150877922773361,"w":0.8604150414466858},"size":5.920830726623535,"orthographic":false}